pyclpu
