Metadata-Version: 2.1
Name: pyclpu
Version: 1.1.6
Summary: CLPU Utilities
Home-page: https://git.clpu.es/mehret/pyclpu
Author: Michael Ehret
Author-email: mehret@clpu.es
License: MIT
Classifier: Development Status :: 1 - Planning
Classifier: Intended Audience :: Science/Research
Classifier: Programming Language :: Python :: 3.11
License-File: LICENSE
